visualqc/__alignment__.py
visualqc/__defacing__.py
visualqc/__diffusion__.py
visualqc/__freesurfer__.py
visualqc/__func_mri__.py
visualqc/__init__.py
visualqc/__t1_mri__.py
visualqc/_version.py
visualqc/alignment.py
visualqc/config.py
visualqc/defacing.py
visualqc/diffusion.py
visualqc/features.py
visualqc/freesurfer.py
visualqc/functional_mri.py
visualqc/image_utils.py
visualqc/interfaces.py
visualqc/outliers.py
visualqc/ratings_db.py
visualqc/readers.py
visualqc/t1_mri.py
visualqc/utils.py
visualqc/workflows.py
visualqc/resources/atlases/mni_icbm152_nl_VI_nifti/COPYING
visualqc/resources/atlases/mni_icbm152_nl_VI_nifti/README
visualqc/resources/atlases/mni_icbm152_nl_VI_nifti/icbm_avg_152_t1_tal_nlin_symmetric_VI.nii
visualqc/resources/atlases/mni_icbm152_nl_VI_nifti/icbm_avg_152_t1_tal_nlin_symmetric_VI_eye_mask.nii
visualqc/resources/atlases/mni_icbm152_nl_VI_nifti/icbm_avg_152_t1_tal_nlin_symmetric_VI_headmask.nii
visualqc/resources/atlases/mni_icbm152_nl_VI_nifti/icbm_avg_152_t1_tal_nlin_symmetric_VI_mask.nii
visualqc-0.7.dist-info/METADATA
visualqc-0.7.dist-info/WHEEL
visualqc-0.7.dist-info/entry_points.txt
visualqc-0.7.dist-info/licenses/AUTHORS.rst
visualqc-0.7.dist-info/licenses/LICENSE
visualqc-0.7.dist-info/RECORD
