Metadata-Version: 2.4
Name: VisualQC
Version: 0.7
Summary: Assistive tool for the quality control of neuroimaging data
Project-URL: Homepage, https://github.com/raamana/visualqc
Author-email: Pradeep Reddy Raamana <raamana@gmail.com>
License-Expression: Apache-2.0
License-File: AUTHORS.rst
License-File: LICENSE
Keywords: visualqc
Classifier: Development Status :: 4 - Beta
Classifier: Programming Language :: Python
Classifier: Programming Language :: Python :: 3.7
Classifier: Programming Language :: Python :: 3.8
Classifier: Programming Language :: Python :: 3.9
Classifier: Programming Language :: Python :: 3.10
Classifier: Programming Language :: Python :: 3.11
Classifier: Programming Language :: Python :: Implementation :: CPython
Classifier: Programming Language :: Python :: Implementation :: PyPy
Requires-Python: >=3.7
Requires-Dist: matplotlib>=2.1.1
Requires-Dist: mrivis
Requires-Dist: nibabel
Requires-Dist: numpy
Requires-Dist: packaging
Requires-Dist: pybids
Requires-Dist: scikit-learn
Requires-Dist: scipy
